README.rst
setup.cfg
setup.py
reflection/__init__.py
reflection/constants.py
reflection/core.py
reflection/events.py
reflection/styles.py
reflection.egg-info/PKG-INFO
reflection.egg-info/SOURCES.txt
reflection.egg-info/dependency_links.txt
reflection.egg-info/top_level.txt