Metadata-Version: 1.1
Name: reflection
Version: 0.0.2
Summary: A modern and pythonic GUI library
Home-page: https://github.com/Coal0/reflection
Author: coal0
Author-email: charcoalzx@protonmail.com
License: MIT
Keywords: GUI,interface,tkinter,tk
Platform: UNKNOWN
Classifier: Development Status :: 3 - Alpha
Classifier: Intended Audience :: Developers
Classifier: Intended Audience :: System Administrators
Classifier: License :: OSI Approved :: MIT License
Classifier: Operating System :: OS Independent
Classifier: Programming Language :: Python :: 2
Classifier: Programming Language :: Python :: 3
Classifier: Topic :: Multimedia :: Graphics
Classifier: Topic :: Software Development :: Libraries
